valohai/__init__.py
valohai/config.py
valohai/consts.py
valohai/controller_api.py
valohai/distributed.py
valohai/execution.py
valohai/inputs.py
valohai/metadata.py
valohai/output_properties.py
valohai/outputs.py
valohai/parameters.py
valohai/paths.py
valohai/prepare_impl.py
valohai/py.typed
valohai/triggers.py
valohai/types.py
valohai/webhooks.py
valohai/yaml.py
valohai/internals/__init__.py
valohai/internals/api_calls.py
valohai/internals/compression.py
valohai/internals/download.py
valohai/internals/download_type.py
valohai/internals/files.py
valohai/internals/global_state.py
valohai/internals/global_state_loader.py
valohai/internals/guid.py
valohai/internals/input_info.py
valohai/internals/inputs.py
valohai/internals/merge.py
valohai/internals/notebooks.py
valohai/internals/parameters.py
valohai/internals/parsing.py
valohai/internals/pipeline.py
valohai/internals/utils.py
valohai/internals/vfs.py
valohai/internals/yaml.py
valohai/internals/distributed_config/__init__.py
valohai/internals/distributed_config/distributed_config.py
valohai/internals/distributed_config/member.py
valohai/internals/distributed_config/utils.py
valohai_utils-0.7.0.dist-info/METADATA
valohai_utils-0.7.0.dist-info/WHEEL
valohai_utils-0.7.0.dist-info/licenses/LICENSE
valohai_utils-0.7.0.dist-info/RECORD
