Metadata-Version: 2.4
Name: valohai-utils
Version: 0.7.0
Author-email: Valohai <hait@valohai.com>
License-Expression: MIT
License-File: LICENSE
Requires-Python: >=3.8
Requires-Dist: requests
Requires-Dist: valohai-papi>=0.1.1
Requires-Dist: valohai-yaml>=0.22.0
